TME6/REG/reg.vhdl
library ieee;
use ieee.std_logic_1164.all;
use ieee.numeric_std.all;

entity Reg is
	port(
	-- Write Port 1 prioritaire
		wdata1		: in Std_Logic_Vector(31 downto 0); --port écriture data1 
		wadr1			: in Std_Logic_Vector(3 downto 0); --registre écriture data1
		wen1			: in Std_Logic; --bit enable data1, si = 1 alors on écrit

	-- Write Port 2 non prioritaire
		wdata2		: in Std_Logic_Vector(31 downto 0);--port écriture data2
		wadr2			: in Std_Logic_Vector(3 downto 0);--registre écriture data2
		wen2			: in Std_Logic;--bit enable data2, si = 1 alors on écrit

	-- Write CSPR Port
		wcry			: in Std_Logic;--valeur de la retenue en écriture
		wzero			: in Std_Logic; --valeur de flag z
		wneg			: in Std_Logic;--valeur de flag n
		wovr			: in Std_Logic; --valeur de flag v
		cspr_wb		: in Std_Logic;--bit enable des flags, si = 1 alors on écrit
		
	-- Read Port 1 32 bits
		reg_rd1		: out Std_Logic_Vector(31 downto 0); --valeur du registre lue
		radr1			: in Std_Logic_Vector(3 downto 0); -- registre lu
		reg_v1		: out Std_Logic; --bit de validité du registre lu, que l'on envoie à l'étage décode pour analyse

	-- Read Port 2 32 bits
		reg_rd2		: out Std_Logic_Vector(31 downto 0); --valeur du registre lue
		radr2			: in Std_Logic_Vector(3 downto 0);-- registre lu
		reg_v2		: out Std_Logic;--bit de validité du registre lu, que l'on envoie à l'étage décode pour analyse

	-- Read Port 3 32 bits
		reg_rd3		: out Std_Logic_Vector(31 downto 0);
		radr3			: in Std_Logic_Vector(3 downto 0);
		reg_v3		: out Std_Logic;

	-- Read Port 4 5 bits
		reg_rd4		: out Std_Logic_Vector(4 downto 0);
		radr4			: in Std_Logic_Vector(3 downto 0);
		reg_v4		: out Std_Logic;

	-- read CSPR Port
		reg_cry		: out Std_Logic; --valeur des flags lues
		reg_zero		: out Std_Logic;
		reg_neg		: out Std_Logic;
		reg_cznv		: out Std_Logic; --bit de validité de c,z et n
		reg_ovr		: out Std_Logic; --valeur de l'overflow
		reg_vv		: out Std_Logic;--bit de validité de l'overflow
		
	-- Invalidate Port 
		inval_adr1	: in Std_Logic_Vector(3 downto 0); --registres invalidé par decode, donc impossible d'écrire dedans
		inval1		: in Std_Logic; --valeur du bit de validité

		inval_adr2	: in Std_Logic_Vector(3 downto 0);
		inval2		: in Std_Logic;

		inval_czn	: in Std_Logic;
		inval_ovr	: in Std_Logic;

	-- PC
		reg_pc		: out Std_Logic_Vector(31 downto 0);
		reg_pcv		: out Std_Logic;
		inc_pc		: in Std_Logic;
	
	-- global interface
		ck				: in Std_Logic;
		reset_n		: in Std_Logic;
		vdd			: in bit;
		vss			: in bit);
end Reg;

architecture Behavior OF Reg is
	type Registres is array (15 downto 0) of std_logic_vector(31 downto 0);
	type Bits is array (15 downto 0) of std_logic;
	signal c, ovr, z, n, czn_valid, ovr_valid : std_logic;
	signal	regs : Registres;
	signal  bits_valid : Bits;
	-- on ne peut pas assigner à un même signal depuis deux process
	begin

		write_regs: process(wen1, wen2, wadr1, wadr2, cspr_wb, wcry, wovr, wzero, wneg, wdata1, wdata2, reset_n)
			variable index : integer;
			variable pc_int: integer;
			begin
				if reset_n = '1' then
					-- Write to register 
					-- Le calcul de pc est fait par l'étage exec, dans le cas d'un branchement la nouvelle adresse de pc est contenue dans wdata1
					-- le registre écrit aura donc la valeur 15 (i.e. index = 15)

					--Si le bit de validité en écriture vaut '1' alors on propage la donnée
					if wen2 = '1' then 
						index := to_integer(unsigned(wadr2));
						regs(index) <= wdata2;
						bits_valid(index) <= '1';
					end if;

					if wen1 = '1' then 
						index := to_integer(unsigned(wadr1));
						regs(index) <= wdata1;
						bits_valid(index) <= '1';
					end if;

					--Maj flags
					
					if cspr_wb = '1' then 
						c <= wcry;
						ovr <= wovr; 
						z <= wzero; 
						n <= wneg;
					end if;
					
					--PC est par défaut incrémenter à chaque cycle d'horloge
					
					if rising_edge(ck) then
						pc_int := to_integer(unsigned(regs(15)));
						if inc_pc = '0' then 
							pc_int := pc_int + 4;
						end if;
						regs(15) <= std_logic_vector(to_unsigned(pc_int, 32));
						reg_pc <= std_logic_vector(to_unsigned(pc_int, 32));
						reg_pcv <= bits_valid(15);
					end if;	
				
				else --cas où reset_n = '0'
					czn_valid <= '0';
					ovr_valid <= '0';
				end if;
		end process write_regs;


		read_regs: 	process(radr1, radr2, radr3, c, z, n, ovr, czn_valid, ovr_valid, regs, bits_valid,  reset_n)
			variable index : integer;
			begin
				if reset_n = '1' then
					-- Read registers
					index := to_integer(unsigned(radr1));
					reg_rd1 <= regs(index);
					reg_v1 <= bits_valid(index);
					
					index := to_integer(unsigned(radr2));
					reg_rd2 <= regs(index);
					reg_v2 <= bits_valid(index);
					
					index := to_integer(unsigned(radr3));
					reg_rd3 <= regs(index);
					reg_v3 <= bits_valid(index);

					index := to_integer(unsigned(radr4));
					reg_rd4 <= regs(index)(4 downto 0);
					reg_v4 <= bits_valid(index);
					--read flags
					reg_cry <= c; 
					reg_zero <= z;
					reg_neg <= n; 
					reg_ovr <= ovr; 
					reg_cznv <= czn_valid;
					reg_vv <= ovr_valid;

				end if;
		end process read_regs;

		--Invalidation des registres par DEC
		-- ex : ADD r0,r1,r2
		-- On invalide r0 à l'étage decode et à la fin de l'étage exe on écrit dans r0 et ainsi on le revalide
		invalid_regs: process(inval_adr1, inval1, inval_adr2, inval2, inval_ovr, inval_czn, reset_n)
			variable index : integer;
			begin
				if reset_n = '1' then
					if inval1 = '0' then 
						index := to_integer(unsigned(inval_adr1));
						bits_valid(index) <=	'0';			
					end if; 
					if inval2 = '0' then 
						index := to_integer(unsigned(inval_adr2));
						bits_valid(index) <=	'0';			
					end if; 

					if inval_czn = '0' then 
						czn_valid <= '0'; 
					end if; 

					if inval_ovr = '0' then 
						ovr_valid <= '0';
					end if;  
				end if;
		end process invalid_regs;


		--print_regs: process(regs)
		--function to_string ( a: std_logic_vector) return string is
	 --     variable b : string (1 to a'length) := (others => NUL);
	 --     variable stri : integer := 1; 
	 --   begin
	 --     for i in a'range loop
	 --         b(stri) := std_logic'image(a((i)))(2);  
	 --     stri := stri+1;
	 --     end loop;
	 --   return b;
	 --   end function;
		--begin 
		--	for i in 0 to 15 loop
		--		report "regs" & integer'image(i) & " : " & to_string(regs(i));
		--	end loop;

		--end process; 

end Behavior;

TME6/REG/reg_tb.vhdl
LIBRARY IEEE;
USE IEEE.STD_LOGIC_1164.ALL ;
USE IEEE.numeric_std.ALL ;
use ieee.math_real.all;


entity reg_tb is
end entity;

architecture behavior of reg_tb is
	SIGNAL	wdata1			:  Std_Logic_Vector(31 downto 0);
	SIGNAL	wadr1			:  Std_Logic_Vector(3 downto 0);
	SIGNAL	wen1			:  Std_Logic;

	-- Write Port 2 non prioritaire
	SIGNAL	wdata2			:  Std_Logic_Vector(31 downto 0);
	SIGNAL	wadr2			:  Std_Logic_Vector(3 downto 0);
	SIGNAL	wen2			:  Std_Logic;

	-- Write CSPR Port
	SIGNAL	wcry			:  Std_Logic;
	SIGNAL	wzero			:  Std_Logic;
	SIGNAL	wneg			:  Std_Logic;
	SIGNAL	wovr			:  Std_Logic;
	SIGNAL	cspr_wb			:  Std_Logic;
		
	-- Read Port 1 32 bits
	SIGNAL	reg_rd1			:  Std_Logic_Vector(31 downto 0);
	SIGNAL	radr1			:  Std_Logic_Vector(3 downto 0);
	SIGNAL	reg_v1			:  Std_Logic;

	-- Read Port 2 32 bits
	SIGNAL	reg_rd2			:  Std_Logic_Vector(31 downto 0);
	SIGNAL	radr2			:  Std_Logic_Vector(3 downto 0);
	SIGNAL	reg_v2			:  Std_Logic;

	-- Read Port 3 32 bits
	SIGNAL	reg_rd3			:  Std_Logic_Vector(31 downto 0);
	SIGNAL	radr3			:  Std_Logic_Vector(3 downto 0);
	SIGNAL	reg_v3			:  Std_Logic;

	-- Read Port 4 5 bits
	SIGNAL	reg_rd4			:  Std_Logic_Vector(4 downto 0);
	SIGNAL	radr4			:  Std_Logic_Vector(3 downto 0);
	SIGNAL	reg_v4			:  Std_Logic;

	-- read CSPR Port
	SIGNAL	reg_cry			:  Std_Logic;
	SIGNAL	reg_zero		:  Std_Logic;
	SIGNAL	reg_neg			:  Std_Logic;
	SIGNAL	reg_cznv		:  Std_Logic;
	SIGNAL	reg_ovr			:  Std_Logic;
	SIGNAL	reg_vv			:  Std_Logic;
		
	-- Invalidate Port 
	SIGNAL	inval_adr1	:  Std_Logic_Vector(3 downto 0);
	SIGNAL	inval1		:  Std_Logic;

	SIGNAL	inval_adr2	:  Std_Logic_Vector(3 downto 0);
	SIGNAL	inval2		:  Std_Logic;

	SIGNAL	inval_czn	:  Std_Logic;
	SIGNAL	inval_ovr	:  Std_Logic;

	-- PC
	SIGNAL	reg_pc		:  Std_Logic_Vector(31 downto 0);
	SIGNAL	reg_pcv		:  Std_Logic;
	SIGNAL	inc_pc		:  Std_Logic;
	
	-- global interface
	SIGNAL	ck				:  Std_Logic;
	SIGNAL	reset_n			:  Std_Logic;
	SIGNAL	vdd				:  bit;
	SIGNAL	vss				:  bit;

	component reg is
	port(
	-- Write Port 1 prioritaire
		wdata1		: in Std_Logic_Vector(31 downto 0);
		wadr1			: in Std_Logic_Vector(3 downto 0);
		wen1			: in Std_Logic;

	-- Write Port 2 non prioritaire
		wdata2		: in Std_Logic_Vector(31 downto 0);
		wadr2			: in Std_Logic_Vector(3 downto 0);
		wen2			: in Std_Logic;

	-- Write CSPR Port
		wcry			: in Std_Logic;
		wzero			: in Std_Logic;
		wneg			: in Std_Logic;
		wovr			: in Std_Logic;
		cspr_wb		: in Std_Logic;
		
	-- Read Port 1 32 bits
		reg_rd1		: out Std_Logic_Vector(31 downto 0);
		radr1			: in Std_Logic_Vector(3 downto 0);
		reg_v1		: out Std_Logic;

	-- Read Port 2 32 bits
		reg_rd2		: out Std_Logic_Vector(31 downto 0);
		radr2			: in Std_Logic_Vector(3 downto 0);
		reg_v2		: out Std_Logic;

	-- Read Port 3 32 bits
		reg_rd3		: out Std_Logic_Vector(31 downto 0);
		radr3			: in Std_Logic_Vector(3 downto 0);
		reg_v3		: out Std_Logic;

	-- Read Port 4 5 bits
		reg_rd4		: out Std_Logic_Vector(4 downto 0);
		radr4			: in Std_Logic_Vector(3 downto 0);
		reg_v4		: out Std_Logic;

	-- read CSPR Port
		reg_cry		: out Std_Logic;
		reg_zero		: out Std_Logic;
		reg_neg		: out Std_Logic;
		reg_cznv		: out Std_Logic;
		reg_ovr		: out Std_Logic;
		reg_vv		: out Std_Logic;
		
	-- Invalidate Port 
		inval_adr1	: in Std_Logic_Vector(3 downto 0);
		inval1		: in Std_Logic;

		inval_adr2	: in Std_Logic_Vector(3 downto 0);
		inval2		: in Std_Logic;

		inval_czn	: in Std_Logic;
		inval_ovr	: in Std_Logic;

	-- PC
		reg_pc		: out Std_Logic_Vector(31 downto 0);
		reg_pcv		: out Std_Logic;
		inc_pc		: in Std_Logic;
	
	-- global interface
		ck				: in Std_Logic;
		reset_n		: in Std_Logic;
		vdd			: in bit;
		vss			: in bit);
	end component;

	begin 

	reg_stage: reg port map (
	-- Write Port 1 prioritaire
		wdata1 => wdata1,
		wadr1 => wadr1,
		wen1 => wen1,

	-- Write Port 2 non prioritaire
		wdata2 => wdata2,
		wadr2 => wadr2,
		wen2 => wen2,

	-- Write CSPR Port
		wcry => wcry,
		wzero => wzero,
		wneg => wneg,
		wovr => wovr,
		cspr_wb => cspr_wb,
		
	-- Read Port 1 32 bits
		reg_rd1 => reg_rd1,
		radr1 => radr1,
		reg_v1 => reg_v1,

	-- Read Port 2 32 bits
		reg_rd2 => reg_rd2,
		radr2 => radr2,
		reg_v2 => reg_v2,

	-- Read Port 3 32 bits
		reg_rd3 => reg_rd3,
		radr3 => radr3,
		reg_v3 => reg_v3,

	-- Read Port 4 5 bits
		reg_rd4 => reg_rd4,
		radr4 => radr4,
		reg_v4 => reg_v4,

	-- read CSPR Port
		reg_cry => reg_cry,
		reg_zero => reg_zero,
		reg_neg => reg_neg,
		reg_cznv => reg_cznv,
		reg_ovr => reg_ovr,
		reg_vv => reg_vv,
		
	-- Invalidate Port 
		inval_adr1 => inval_adr1,
		inval1 => inval1,

		inval_adr2 => inval_adr2,
		inval2 => inval2,

		inval_czn => inval_czn,
		inval_ovr => inval_ovr,

	-- PC
		reg_pc => reg_pc,
		reg_pcv => reg_pcv,
		inc_pc => inc_pc,
	
	-- global interface
		ck => ck,
		reset_n => reset_n,
		vdd => vdd,
		vss => vss
		);
	clock_process : PROCESS
	  begin 
	    ck <= '1';
	    WAIT FOR 4 ns;
	    ck <= '0';
	    WAIT FOR 4 ns;
  	end process;

  	reset: process
  		begin
  			reset_n <= '0';
  			wait for 4 ns;
  			reset_n <= '1';
  			wait;
  		end process;


  	tes_tb_process : PROCESS(ck)

	  variable seed1, seed2 : integer := 999;

	  function to_string ( a: std_logic_vector) return string is
	      variable b : string (1 to a'length) := (others => NUL);
	      variable stri : integer := 1; 
	    begin
	      for i in a'range loop
	          b(stri) := std_logic'image(a((i)))(2);  
	      stri := stri+1;
	      end loop;
	    return b;
	    end function;

	    impure FUNCTION rand_slv(len : integer) return std_logic_vector is
	        variable r : real;
	        variable slv : std_logic_vector(len - 1 downto 0);
	        BEGIN
	          for i in slv'range loop
	              uniform(seed1, seed2, r);
	            IF r > 0.5 THEN
	              slv(i) := '1';
	            ELSE
	              slv(i) := '0';
	            END IF;
	          end loop;
	        return slv;
	      END FUNCTION;

    BEGIN
    if rising_edge(ck) then
		wdata1 <= rand_slv(32);
		wadr1 <= rand_slv(4);
		wen1 <= rand_slv(2)(1) ;

		wdata2 <= rand_slv(32);
		wadr2 <= rand_slv(4);
		wen2 <= rand_slv(2)(1) ;
		
		wcry <= rand_slv(2)(1) ;
		wzero <=rand_slv(2)(1) ;
		wneg <=rand_slv(2)(1) ;
		wovr <=rand_slv(2)(1) ;
		cspr_wb <=rand_slv(2)(1) ; --on autorise l'écriture

		radr1 <= (others => '0') ;
		radr2 <= rand_slv(4) ;
		radr3 <= rand_slv(4) ;
		radr4 <= rand_slv(4) ;

		inval_adr1 <= rand_slv(4) ;
		inval_adr2 <= rand_slv(4) ;
		inval_czn <= rand_slv(2)(1) ;
		inval_ovr <= rand_slv(2)(1) ;

		inc_pc <= '1' ;
		
		--wdata1 <= (others=>'1');
		--wadr1 <= "0000";
		--wen1 <= '0' ;

		--wdata2 <= (others=>'0');
		--wadr2 <= "0001";
		--wen2 <= '1' ;
		
		--wcry <= rand_slv(2)(1) ;
		--wzero <=rand_slv(2)(1) ;
		--wneg <=rand_slv(2)(1) ;
		--wovr <=rand_slv(2)(1) ;
		--cspr_wb <=rand_slv(2)(1) ; --on autorise l'écriture

		--radr1 <= "0000" ;
		--radr2 <= "0001" ;
		--radr3 <= rand_slv(4) ;
		--radr4 <= rand_slv(4) ;

		--inval_adr1 <= "0010" ;
		--inval_adr2 <= "0010" ;
		--inval_czn <= '0' ;
		--inval_ovr <= '0';

		--inc_pc <= '1' ;

		report "__________________________________________________";
		report "reset : " & std_logic'image(reset_n)(2);
       report "wdata1 : " & to_string(wdata1);
       report "wdata2 : " & to_string(wdata2); 
       report "wen1 : " & std_logic'image(wen1)(2);
       report "wen2 : " & std_logic'image(wen2)(2);                 
       report "wadr1 : " & to_string(wadr1);
       report "wadr2 : " & to_string(wadr2);

       report "wcry : " & std_logic'image(wcry)(2);
       report "wzero : " & std_logic'image(wzero)(2);
       report "wneg : " & std_logic'image(wneg)(2);
       report "wovr : " & std_logic'image(wovr)(2);
       report "cspr_wb : " & std_logic'image(cspr_wb)(2);

       report "radr1 : " & to_string(radr1); 
  	   report "radr2 : " & to_string(radr2); 
  	   report "radr3 : " & to_string(radr3); 
  	   report "radr4 : " & to_string(radr4);

  	   report "inval_adr1 : " & to_string(inval_adr1);
  	   report "inval_adr2 : " & to_string(inval_adr2);
  	   report "inval_czn : " & std_logic'image(inval_czn)(2);
  	   report "inval_ovr : " & std_logic'image(inval_ovr)(2);
	   report "inc_pc : " & std_logic'image(inc_pc)(2);

	   report "reg_rd1 : " & to_string(reg_rd1);
	   report "reg_rd2 : " & to_string(reg_rd2);
	   report "reg_rd3 : " & to_string(reg_rd3);
	   report "reg_rd4 : " & to_string(reg_rd4);

	   report "reg_v1 : " & std_logic'image(reg_v1)(2);
	   report "reg_v2 : " & std_logic'image(reg_v2)(2);
	   report "reg_v3 : " & std_logic'image(reg_v3)(2);
	   report "reg_v4 : " & std_logic'image(reg_v4)(2);

	   report "reg_cry : " & std_logic'image(reg_cry)(2);
	   report "reg_zero : " & std_logic'image(reg_zero)(2);
	   report "reg_neg : " & std_logic'image(reg_neg)(2);
	   report "reg_cznv : " & std_logic'image(reg_cznv)(2);
	   report "reg_ovr : " & std_logic'image(reg_ovr)(2);
	   report "reg_vv : " & std_logic'image(reg_vv)(2);

	   report "reg_pc : " & to_string(reg_pc);
	   report "reg_pcv : " & std_logic'image(reg_pcv)(2);




    end if;
  END PROCESS tes_tb_process ;     

end architecture behavior;

TME6/REG/reg.vcd
$date
  Thu Oct 28 21:29:58 2021
$end
$version
  GHDL v0
$end
$timescale
  1 fs
$end
$scope module standard $end
$upscope $end
$scope module std_logic_1164 $end
$upscope $end
$scope module numeric_std $end
$upscope $end
$scope module math_real $end
$upscope $end
$scope module reg_tb $end
$var reg 32 ! wdata1[31:0] $end
$var reg 4 " wadr1[3:0] $end
$var reg 1 # wen1 $end
$var reg 32 $ wdata2[31:0] $end
$var reg 4 % wadr2[3:0] $end
$var reg 1 & wen2 $end
$var reg 1 ' wcry $end
$var reg 1 ( wzero $end
$var reg 1 ) wneg $end
$var reg 1 * wovr $end
$var reg 1 + cspr_wb $end
$var reg 32 , reg_rd1[31:0] $end
$var reg 4 - radr1[3:0] $end
$var reg 1 . reg_v1 $end
$var reg 32 / reg_rd2[31:0] $end
$var reg 4 0 radr2[3:0] $end
$var reg 1 1 reg_v2 $end
$var reg 32 2 reg_rd3[31:0] $end
$var reg 4 3 radr3[3:0] $end
$var reg 1 4 reg_v3 $end
$var reg 5 5 reg_rd4[4:0] $end
$var reg 4 6 radr4[3:0] $end
$var reg 1 7 reg_v4 $end
$var reg 1 8 reg_cry $end
$var reg 1 9 reg_zero $end
$var reg 1 : reg_neg $end
$var reg 1 ; reg_cznv $end
$var reg 1 < reg_ovr $end
$var reg 1 = reg_vv $end
$var reg 4 > inval_adr1[3:0] $end
$var reg 1 ? inval1 $end
$var reg 4 @ inval_adr2[3:0] $end
$var reg 1 A inval2 $end
$var reg 1 B inval_czn $end
$var reg 1 C inval_ovr $end
$var reg 32 D reg_pc[31:0] $end
$var reg 1 E reg_pcv $end
$var reg 1 F inc_pc $end
$var reg 1 G ck $end
$var reg 1 H reset_n $end
$var reg 1 I vdd $end
$var reg 1 J vss $end
$scope module reg_stage $end
$var reg 32 K wdata1[31:0] $end
$var reg 4 L wadr1[3:0] $end
$var reg 1 M wen1 $end
$var reg 32 N wdata2[31:0] $end
$var reg 4 O wadr2[3:0] $end
$var reg 1 P wen2 $end
$var reg 1 Q wcry $end
$var reg 1 R wzero $end
$var reg 1 S wneg $end
$var reg 1 T wovr $end
$var reg 1 U cspr_wb $end
$var reg 32 V reg_rd1[31:0] $end
$var reg 4 W radr1[3:0] $end
$var reg 1 X reg_v1 $end
$var reg 32 Y reg_rd2[31:0] $end
$var reg 4 Z radr2[3:0] $end
$var reg 1 [ reg_v2 $end
$var reg 32 \ reg_rd3[31:0] $end
$var reg 4 ] radr3[3:0] $end
$var reg 1 ^ reg_v3 $end
$var reg 5 _ reg_rd4[4:0] $end
$var reg 4 ` radr4[3:0] $end
$var reg 1 a reg_v4 $end
$var reg 1 b reg_cry $end
$var reg 1 c reg_zero $end
$var reg 1 d reg_neg $end
$var reg 1 e reg_cznv $end
$var reg 1 f reg_ovr $end
$var reg 1 g reg_vv $end
$var reg 4 h inval_adr1[3:0] $end
$var reg 1 i inval1 $end
$var reg 4 j inval_adr2[3:0] $end
$var reg 1 k inval2 $end
$var reg 1 l inval_czn $end
$var reg 1 m inval_ovr $end
$var reg 32 n reg_pc[31:0] $end
$var reg 1 o reg_pcv $end
$var reg 1 p inc_pc $end
$var reg 1 q ck $end
$var reg 1 r reset_n $end
$var reg 1 s vdd $end
$var reg 1 t vss $end
$var reg 1 u c $end
$var reg 1 v ovr $end
$var reg 1 w z $end
$var reg 1 x n $end
$var reg 1 y czn_valid $end
$var reg 1 z ovr_valid $end
$var  { regs $end
$var reg 16 | bits_valid[15:0] $end
$upscope $end
$upscope $end
$enddefinitions $end
#0
bUUUUUUUUUUUUUUUUUUUUUUUUUUUUUUUU !
bUUUU "
U#
bUUUUUUUUUUUUUUUUUUUUUUUUUUUUUUUU $
bUUUU %
U&
U'
U(
U)
U*
U+
bUUUUUUUUUUUUUUUUUUUUUUUUUUUUUUUU ,
bUUUU -
U.
bUUUUUUUUUUUUUUUUUUUUUUUUUUUUUUUU /
bUUUU 0
U1
bUUUUUUUUUUUUUUUUUUUUUUUUUUUUUUUU 2
bUUUU 3
U4
bUUUUU 5
bUUUU 6
U7
U8
U9
U:
U;
U<
U=
bUUUU >
U?
bUUUU @
UA
UB
UC
bUUUUUUUUUUUUUUUUUUUUUUUUUUUUUUUU D
UE
UF
1G
0H
0I
0J
bUUUUUUUUUUUUUUUUUUUUUUUUUUUUUUUU K
bUUUU L
UM
bUUUUUUUUUUUUUUUUUUUUUUUUUUUUUUUU N
bUUUU O
UP
UQ
UR
US
UT
UU
bUUUUUUUUUUUUUUUUUUUUUUUUUUUUUUUU V
bUUUU W
UX
bUUUUUUUUUUUUUUUUUUUUUUUUUUUUUUUU Y
bUUUU Z
U[
bUUUUUUUUUUUUUUUUUUUUUUUUUUUUUUUU \
bUUUU ]
U^
bUUUUU _
bUUUU `
Ua
Ub
Uc
Ud
Ue
Uf
Ug
bUUUU h
Ui
bUUUU j
Uk
Ul
Um
bUUUUUUUUUUUUUUUUUUUUUUUUUUUUUUUU n
Uo
Up
1q
0r
0s
0t
Uu
Uv
Uw
Ux
Uy
Uz
{
bUUUUUUUUUUUUUUUU |
#4000000
0G
1H
0q
1r
#8000000
b11111111100101100010101000011001 !
b0000 "
0#
b10111111001011110001111111000010 $
b0011 %
0&
0'
0(
1)
1*
0+
b0000 -
b1011 0
b1010 3
b0111 6
0;
b1011 >
b1101 @
0B
1C
1F
1G
b11111111100101100010101000011001 K
b0000 L
0M
b10111111001011110001111111000010 N
b0011 O
0P
0Q
0R
1S
1T
0U
b0000 W
b1011 Z
b1010 ]
b0111 `
0e
b1011 h
b1101 j
0l
1m
1p
1q
0y
#12000000
0G
0q
#16000000
b11111000101001101111000101111010 !
1#
b01100111101000101110010011111011 $
b1001 %
1&
1'
1(
b11111000101001101111000101111010 ,
b1110 0
b1100 3
b1111 6
0=
b0010 >
b1111 @
0C
1G
b11111000101001101111000101111010 K
1M
b01100111101000101110010011111011 N
b1001 O
1P
1Q
1R
b11111000101001101111000101111010 V
b1110 Z
b1100 ]
b1111 `
0g
b0010 h
b1111 j
0m
1q
0z
#20000000
0G
0q
#24000000
b11111100000001110100011101001100 !
b0011 "
b01110101000001010100100110010101 $
b0101 %
0'
0(
0*
b0110 0
b1010 6
b1101 >
b0110 @
1G
b11111100000001110100011101001100 K
b0011 L
b01110101000001010100100110010101 N
b0101 O
0Q
0R
0T
b0110 Z
b1010 `
b1101 h
b0110 j
1q
#28000000
0G
0q
#32000000
b10101001001001110010100000001110 !
b11000110110110110000011111001000 $
b0110 %
0&
1(
0)
1+
b1000 0
b1110 3
b1100 6
08
19
0:
0<
b0110 >
b1100 @
1G
b10101001001001110010100000001110 K
b11000110110110110000011111001000 N
b0110 O
0P
1R
0S
1U
b1000 Z
b1110 ]
b1100 `
0b
1c
0d
0f
b0110 h
b1100 j
1q
0u
0v
1w
0x
#36000000
0G
0q
#40000000
b10100100100100101000111101110010 !
b1111 "
0#
b00101100111110100000010110110010 $
0(
0+
b0111 0
b0110 3
b1101 6
b1000 >
b1001 @
1G
b10100100100100101000111101110010 K
b1111 L
0M
b00101100111110100000010110110010 N
0R
0U
b0111 Z
b0110 ]
b1101 `
b1000 h
b1001 j
1q
#44000000
0G
0q
#48000000
b00001100111011011101100011000111 !
b1010 "
1#
b10001111010101011010010010000010 $
b1001 %
1&
1+
b1111 0
b1101 3
b1110 6
09
b1010 >
b1101 @
1G
b00001100111011011101100011000111 K
b1010 L
1M
b10001111010101011010010010000010 N
b1001 O
1P
1U
b1111 Z
b1101 ]
b1110 `
0c
b1010 h
b1101 j
1q
0w
#52000000
0G
0q
#56000000
b01001011110000001001111001100111 !
b0001 "
b11001011001110101000010100010110 $
b1000 %
0&
1(
1*
0+
b0111 0
b1000 3
b00111 5
b0001 6
b1110 >
b0101 @
1G
b01001011110000001001111001100111 K
b0001 L
b11001011001110101000010100010110 N
b1000 O
0P
1R
1T
0U
b0111 Z
b1000 ]
b00111 _
b0001 `
b1110 h
b0101 j
1q
#60000000
0G
0q
#64000000
b00110110000000011101001110110001 !
b0000 "
b01001000111111010110000001110011 $
b0010 %
0(
b00110110000000011101001110110001 ,
b1111 0
b00001100111011011101100011000111 2
b1010 3
bUUUUU 5
b1100 6
b0111 >
b0001 @
1G
b00110110000000011101001110110001 K
b0000 L
b01001000111111010110000001110011 N
b0010 O
0R
b00110110000000011101001110110001 V
b1111 Z
b00001100111011011101100011000111 \
b1010 ]
bUUUUU _
b1100 `
b0111 h
b0001 j
1q
#68000000
0G
0q
#72000000
b01110000100011011011110111010010 !
b0001 "
b11000001000110001011011001110100 $
b1000 %
1&
0*
b0111 0
bUUUUUUUUUUUUUUUUUUUUUUUUUUUUUUUU 2
b1011 3
b00010 5
b1001 6
b1000 @
1C
1G
b01110000100011011011110111010010 K
b0001 L
b11000001000110001011011001110100 N
b1000 O
1P
0T
b0111 Z
bUUUUUUUUUUUUUUUUUUUUUUUUUUUUUUUU \
b1011 ]
b00010 _
b1001 `
b1000 j
1m
1q
#76000000
0G
0q
#80000000
b00000111001100001001111101000011 !
b0010 "
b01100100000011000100101100000100 $
b1011 %
0&
1*
b01110000100011011011110111010010 /
b0001 0
b0110 3
bUUUUU 5
b1011 6
b0100 >
b0101 @
0C
1G
b00000111001100001001111101000011 K
b0010 L
b01100100000011000100101100000100 N
b1011 O
0P
1T
b01110000100011011011110111010010 Y
b0001 Z
b0110 ]
bUUUUU _
b1011 `
b0100 h
b0101 j
0m
1q
#84000000
0G
0q
#88000000
b01101100011100101110010110010110 !
b0011 "
b00101100001110011110000011011001 $
b0110 %
1&
bUUUUUUUUUUUUUUUUUUUUUUUUUUUUUUUU /
b1111 0
b01101100011100101110010110010110 2
b0011 3
b1100 6
b1100 >
b1000 @
1C
1G
b01101100011100101110010110010110 K
b0011 L
b00101100001110011110000011011001 N
b0110 O
1P
bUUUUUUUUUUUUUUUUUUUUUUUUUUUUUUUU Y
b1111 Z
b01101100011100101110010110010110 \
b0011 ]
b1100 `
b1100 h
b1000 j
1m
1q
#92000000
0G
0q
#96000000
b11110101011110110111111111111010 !
b1010 "
b11100101101010110001011001001110 $
b0000 %
0&
1'
0*
b11000001000110001011011001110100 /
b1000 0
bUUUUUUUUUUUUUUUUUUUUUUUUUUUUUUUU 2
b1101 3
b11001 5
b0110 6
b1011 >
b1100 @
1B
1G
b11110101011110110111111111111010 K
b1010 L
b11100101101010110001011001001110 N
b0000 O
0P
1Q
0T
b11000001000110001011011001110100 Y
b1000 Z
bUUUUUUUUUUUUUUUUUUUUUUUUUUUUUUUU \
b1101 ]
b11001 _
b0110 `
b1011 h
b1100 j
1l
1q
#100000000
0G
0q
#104000000
b00000111001010111101100001110000 !
b1110 "
0#
b01110010000011100000011100000111 $
b0110 %
1&
0'
1(
1)
1+
bUUUUUUUUUUUUUUUUUUUUUUUUUUUUUUUU /
b1011 0
b10101 5
b0101 6
19
1:
b0010 >
b0010 @
0B
0C
1G
b00000111001010111101100001110000 K
b1110 L
0M
b01110010000011100000011100000111 N
b0110 O
1P
0Q
1R
1S
1U
bUUUUUUUUUUUUUUUUUUUUUUUUUUUUUUUU Y
b1011 Z
b10101 _
b0101 `
1c
1d
b0010 h
b0010 j
0l
0m
1q
1w
1x
#108000000
0G
0q
#112000000
b11010110001000001001100001100011 !
b1101 "
b01010100001001101011101010101110 $
b1110 %
0+
b01101100011100101110010110010110 /
b0011 0
b11110101011110110111111111111010 2
b1010 3
b00010 5
b1001 6
b1101 >
1B
1C
1G
b11010110001000001001100001100011 K
b1101 L
b01010100001001101011101010101110 N
b1110 O
0U
b01101100011100101110010110010110 Y
b0011 Z
b11110101011110110111111111111010 \
b1010 ]
b00010 _
b1001 `
b1101 h
1l
1m
1q
#116000000
0G
0q
#120000000
b00011001000010010001100010100001 !
b0110 "
1#
b01111000100001101010011100010000 $
b1000 %
1*
1+
b01110000100011011011110111010010 /
b0001 0
b01111000100001101010011100010000 2
b1000 3
b00001 5
b0110 6
1<
b1010 >
b0111 @
1G
b00011001000010010001100010100001 K
b0110 L
1M
b01111000100001101010011100010000 N
b1000 O
1T
1U
b01110000100011011011110111010010 Y
b0001 Z
b01111000100001101010011100010000 \
b1000 ]
b00001 _
b0110 `
1f
b1010 h
b0111 j
1q
1v
#124000000
0G
0q
