TME5/Shifter/shifter.vhdl
----------
--shifter
----------

LIBRARY IEEE ;
USE IEEE.STD_LOGIC_1164.ALL;
USE IEEE.NUMERIC_STD.ALL ;
USE IEEE.MATH_REAL.ALL ;

ENTITY Shifter IS
	PORT(
    shift_lsl : IN  Std_Logic;-- permet de dire quel type de shift on effectue
    shift_lsr : IN  Std_Logic;
    shift_asr : IN  Std_Logic;
    shift_ror : IN  Std_Logic;
    shift_rrx : IN  Std_Logic;
    shift_val : IN  Std_Logic_Vector(4 downto 0);--valeur du shift du 5 bit
    din       : IN  Std_Logic_Vector(31 downto 0); --valeur d'entrée 
    cin       : IN  Std_Logic;
    dout      : OUT Std_Logic_Vector(31 downto 0); -- valeur de sortie
    cout      : OUT Std_Logic;
    -- global interface
    vdd       : IN  bit;
    vss       : IN  bit );
END Shifter;

ARCHITECTURE behavior OF Shifter IS
BEGIN
shifter_process_1 :PROCESS(shift_lsl,shift_lsr,shift_ror,shift_rrx,shift_val,din)
    
    VARIABLE immediat_shift : integer ;

    --On va définir des fonctions effectuant chacun des shift. Le bit 32 recupèrera toujours la carry

    FUNCTION shifte_left (a : Std_Logic_Vector(31 downto 0); b : integer) RETURN Std_Logic_Vector IS
        VARIABLE valeur_retour : Std_Logic_Vector(32 downto 0) ;
        BEGIN
            valeur_retour(32) := a(31) ;
            --On met à 0 toutes les valeurs en dessous de la valeur du shift 
            initialisation_des_zeros : FOR j IN 0 TO (b-1) loop
                    valeur_retour(j) := '0' ;
            END LOOP initialisation_des_zeros ;

            parcours_de_a : FOR i IN b TO (a'length-1) loop
                    valeur_retour(i) := a(i-b) ;
            END LOOP parcours_de_a ;

    RETURN valeur_retour ;
    END FUNCTION ;

    FUNCTION shifte_right (a : Std_Logic_Vector(31 downto 0); b : integer) RETURN Std_Logic_Vector IS
        VARIABLE valeur_retour : Std_Logic_Vector(32 downto 0) ;
        BEGIN
            valeur_retour(32) := a(0) ; -- on récupère a(0) que l'on stocke dans la carry

            --On met a 0 toutes les valeurs au dessus du shift
            initialisation_des_zeros : FOR j IN 0 TO b loop
                    valeur_retour(a'length-1-j):= '0' ;
            END LOOP initialisation_des_zeros ;

            parcours_de_a : FOR i IN 0 TO (a'length-1-(b+1)) loop
                    valeur_retour(i) := a(i+b) ;
            END LOOP parcours_de_a ;

    RETURN valeur_retour ;
    END FUNCTION ;

    FUNCTION shifte_asr (a : Std_Logic_Vector(31 downto 0); b : integer) RETURN Std_Logic_Vector IS
        VARIABLE valeur_retour : Std_Logic_Vector(32 downto 0) ;
        BEGIN
            valeur_retour(32) := a(0) ; -- recupere la retenue
            valeur_retour(31) := a(31) ; --on récupère le bit de signe
            initialisation_des_zeros : FOR j   IN 0 TO b loop
                    valeur_retour(a'length-(j+1)) := '0' ;
            END LOOP ;

            parcours_de_a : FOR i IN 0 TO (a'length-1-(b+1)) loop
                    valeur_retour(i) := a(i+b) ;
            END LOOP ;
            

    RETURN valeur_retour ;
    END FUNCTION ;

    FUNCTION shifte_ror (a : Std_Logic_Vector; b : integer) RETURN Std_Logic_Vector IS
            VARIABLE valeur_retour : Std_Logic_Vector(32 downto 0) ;
        BEGIN
            valeur_retour(32) := a(0) ; -- on stocke a(0) dans la carry
            FOR i IN 0 TO (a'length-1) LOOP
                --il faut faire une disjonction des cas pour effectuer la rotation correctement
                IF i < b THEN 
                    valeur_retour(a'length-1-i) := a(i) ;
                else
                    valeur_retour(a'length-1-i) := a(a'length-1+b-i) ;
                END IF ;
            END LOOP;
    RETURN valeur_retour ;
    END FUNCTION ;

    FUNCTION shifte_rrx (a : Std_Logic_Vector; carry_in : std_logic) RETURN Std_Logic_Vector IS
            VARIABLE valeur_retour : Std_Logic_Vector(32 downto 0) ;
        BEGIN
            valeur_retour(32) := a(0) ; -- on stocke a(0) dans la carry
            valeur_retour(31) := carry_in ;
            FOR i IN 0 TO (a'length-2) LOOP
                    valeur_retour(i) := a(i+1) ;
            END LOOP;
    RETURN valeur_retour ;
    END FUNCTION ;


    BEGIN

    immediat_shift := to_integer(UNSIGNED(shift_val)) ;

    IF(shift_lsl = '1') THEN
            dout <= shifte_left(din,immediat_shift)(31 downto 0) ;
            cout <= shifte_left(din,immediat_shift)(32) ;
    ELSIF (shift_lsr = '1') THEN
            dout <= shifte_right(din,immediat_shift)(31 downto 0) ;
            cout <= shifte_right(din,immediat_shift)(32) ;
    ELSIF (shift_asr = '1') THEN
            dout <= shifte_asr(din,immediat_shift)(31 downto 0) ;
            cout <= shifte_asr(din,immediat_shift)(32) ;
    ELSIF (shift_ror = '1') THEN
            dout <= shifte_ror(din,immediat_shift)(31 downto 0) ;
            cout <= shifte_ror(din,immediat_shift)(32) ;
    ELSIF (shift_rrx = '1') THEN
            dout <= shifte_rrx(din,cin)(31 downto 0) ;
            cout <= shifte_rrx(din,cin)(32) ;
    END IF ;
END PROCESS shifter_process_1 ;
END ARCHITECTURE ;

TME5/Shifter/shifter_tb.vhdl
----------
--shifter_tb
----------

LIBRARY IEEE;
USE IEEE.STD_LOGIC_1164.ALL ;
USE IEEE.numeric_std.ALL ;
use ieee.math_real.all;


ENTITY shifter_tb IS
END ENTITY ;

ARCHITECTURE BEHAVIOR OF shifter_tb IS
  
  SIGNAL shift_lsl,shift_lsr,shift_asr,shift_ror,shift_rrx,cin,cout : std_logic ;
  SIGNAL din,dout : std_logic_vector(31 downto 0) ;
  SIGNAL shift_val : std_logic_vector(4 downto 0) ;
  SIGNAL vdd, vss : bit ;

  COMPONENT shifter IS
    PORT(
    shift_lsl : IN  Std_Logic;-- permet de dire quel type de shift on effectue
    shift_lsr : IN  Std_Logic;
    shift_asr : IN  Std_Logic;
    shift_ror : IN  Std_Logic;
    shift_rrx : IN  Std_Logic;
    shift_val : IN  Std_Logic_Vector(4 downto 0);--valeur du shift du 5 bit
    din       : IN  Std_Logic_Vector(31 downto 0); --valeur d'entrée 
    cin       : IN  Std_Logic;
    dout      : OUT Std_Logic_Vector(31 downto 0); -- valeur de sortie
    cout      : OUT Std_Logic;
    -- global interface
    vdd       : IN  bit;
    vss       : IN  bit );
  END COMPONENT ;

  BEGIN 

  shifter_0 : shifter port map(shift_lsl => shift_lsl,shift_lsr => shift_lsr, shift_asr => shift_asr, shift_ror => shift_ror, shift_rrx => shift_rrx, shift_val => shift_val, din => din, cin => cin, dout => dout, cout => cout, vdd => vdd, vss => vss) ;
  
  tes_tb_process : PROCESS

  variable seed1, seed2 : integer := 999;

  function to_string ( a: std_logic_vector) return string is
      variable b : string (1 to a'length) := (others => NUL);
      variable stri : integer := 1; 
    begin
      for i in a'range loop
          b(stri) := std_logic'image(a((i)))(2);  
      stri := stri+1;
      end loop;
    return b;
    end function;

    impure FUNCTION rand_slv(len : integer) return std_logic_vector is
        variable r : real;
        variable slv : std_logic_vector(len - 1 downto 0);
        BEGIN
          for i in slv'range loop
              uniform(seed1, seed2, r);
            IF r > 0.5 THEN
              slv(i) := '1';
            ELSE
              slv(i) := '0';
            END IF;
          end loop;
        return slv;
      END FUNCTION;

    BEGIN

    --TEST LSL

    shift_lsl <= '1' ;
    shift_lsr <= '0' ;
    shift_asr <= '0' ;
    shift_ror <= '0' ;
    shift_rrx <= '0' ;
    din <= rand_slv(32) ;
    shift_val <= rand_slv(5) ;
    report "shift_lsl :" & std_logic'image(shift_lsl)(2) ;
    report "shift_lsr :" & std_logic'image(shift_lsr)(2) ;
    report "shift_asr :" & std_logic'image(shift_asr)(2) ;
    report "shift_ror :" & std_logic'image(shift_ror)(2) ;
    report "shift_rrx :" & std_logic'image(shift_rrx)(2) ;

    report "shift_val : " &to_string(shift_val) ;

    report "din : " &to_string(din) ;
    report "cin :" & std_logic'image(cin)(2) ; 

    report "dout : " &to_string(dout) ;
    report "cout :" & std_logic'image(cout)(2) ;
    wait for 4 ns ;

    --TEST LSR

    shift_lsl <= '0' ;
    shift_lsr <= '1' ;
    shift_asr <= '0' ;
    shift_ror <= '0' ;
    shift_rrx <= '0' ;

    din <= rand_slv(32) ;
    shift_val <= rand_slv(5) ;
    report "shift_lsl :" & std_logic'image(shift_lsl)(2) ;
    report "shift_lsr :" & std_logic'image(shift_lsr)(2) ;
    report "shift_asr :" & std_logic'image(shift_asr)(2) ;
    report "shift_ror :" & std_logic'image(shift_ror)(2) ;
    report "shift_rrx :" & std_logic'image(shift_rrx)(2) ;

    report "shift_val : " &to_string(shift_val) ;

    report "din : " &to_string(din) ;
    report "cin :" & std_logic'image(cin)(2) ; 

    report "dout : " &to_string(dout) ;
    report "cout :" & std_logic'image(cout)(2) ;
    wait for 4 ns ;

    --TEST ASR

    shift_lsl <= '0' ;
    shift_lsr <= '0' ;
    shift_asr <= '1' ;
    shift_ror <= '0' ;
    shift_rrx <= '0' ;
    din <= rand_slv(32) ;
    shift_val <= rand_slv(5) ;
    report "shift_lsl :" & std_logic'image(shift_lsl)(2) ;
    report "shift_lsr :" & std_logic'image(shift_lsr)(2) ;
    report "shift_asr :" & std_logic'image(shift_asr)(2) ;
    report "shift_ror :" & std_logic'image(shift_ror)(2) ;
    report "shift_rrx :" & std_logic'image(shift_rrx)(2) ;

    report "shift_val : " &to_string(shift_val) ;

    report "din : " &to_string(din) ;
    report "cin :" & std_logic'image(cin)(2) ; 

    report "dout : " &to_string(dout) ;
    report "cout :" & std_logic'image(cout)(2) ;
    wait for 4 ns ;

    --TEST ROR

    shift_lsl <= '0' ;
    shift_lsr <= '0' ;
    shift_asr <= '0' ;
    shift_ror <= '1' ;
    shift_rrx <= '0' ;
    cin <= '1' ;
    din <= rand_slv(32) ;
    shift_val <= rand_slv(5) ;
    report "shift_lsl :" & std_logic'image(shift_lsl)(2) ;
    report "shift_lsr :" & std_logic'image(shift_lsr)(2) ;
    report "shift_asr :" & std_logic'image(shift_asr)(2) ;
    report "shift_ror :" & std_logic'image(shift_ror)(2) ;
    report "shift_rrx :" & std_logic'image(shift_rrx)(2) ;

    report "shift_val : " &to_string(shift_val) ;

    report "din : " &to_string(din) ;
    report "cin :" & std_logic'image(cin)(2) ; 

    report "dout : " &to_string(dout) ;
    report "cout :" & std_logic'image(cout)(2) ;
    wait for 4 ns ;

    --TEST RRX

    shift_lsl <= '0' ;
    shift_lsr <= '0' ;
    shift_asr <= '0' ;
    shift_ror <= '0' ;
    shift_rrx <= '1' ;
    din <= rand_slv(32) ;
    shift_val <= rand_slv(5) ;
    report "shift_lsl :" & std_logic'image(shift_lsl)(2) ;
    report "shift_lsr :" & std_logic'image(shift_lsr)(2) ;
    report "shift_asr :" & std_logic'image(shift_asr)(2) ;
    report "shift_ror :" & std_logic'image(shift_ror)(2) ;
    report "shift_rrx :" & std_logic'image(shift_rrx)(2) ;

    report "shift_val : " &to_string(shift_val) ;

    report "din : " &to_string(din) ;
    report "cin :" & std_logic'image(cin)(2) ; 

    report "dout : " &to_string(dout) ;
    report "cout :" & std_logic'image(cout)(2) ;
    wait for 4 ns ;
    
    END PROCESS tes_tb_process ;     
     

    END ARCHITECTURE ;

TME5/Shifter/shifter.vcd
$date
  Fri Nov  5 14:16:23 2021
$end
$version
  GHDL v0
$end
$timescale
  1 fs
$end
$scope module standard $end
$upscope $end
$scope module std_logic_1164 $end
$upscope $end
$scope module numeric_std $end
$upscope $end
$scope module math_real $end
$upscope $end
$scope module shifter_tb $end
$var reg 1 ! shift_lsl $end
$var reg 1 " shift_lsr $end
$var reg 1 # shift_asr $end
$var reg 1 $ shift_ror $end
$var reg 1 % shift_rrx $end
$var reg 1 & cin $end
$var reg 1 ' cout $end
$var reg 32 ( din[31:0] $end
$var reg 32 ) dout[31:0] $end
$var reg 5 * shift_val[4:0] $end
$var reg 1 + vdd $end
$var reg 1 , vss $end
$scope module shifter_0 $end
$var reg 1 - shift_lsl $end
$var reg 1 . shift_lsr $end
$var reg 1 / shift_asr $end
$var reg 1 0 shift_ror $end
$var reg 1 1 shift_rrx $end
$var reg 5 2 shift_val[4:0] $end
$var reg 32 3 din[31:0] $end
$var reg 1 4 cin $end
$var reg 32 5 dout[31:0] $end
$var reg 1 6 cout $end
$var reg 1 7 vdd $end
$var reg 1 8 vss $end
$upscope $end
$upscope $end
$enddefinitions $end
#0
1!
0"
0#
0$
0%
U&
1'
b11111111100101100010101000011001 (
b11111111100101100010101000011001 )
b00000 *
0+
0,
1-
0.
0/
00
01
b00000 2
b11111111100101100010101000011001 3
U4
b11111111100101100010101000011001 5
16
07
08
#4000000
0!
1"
b01011111100101111000111111100001 (
b00001011111100101111000111111100 )
b00011 *
0-
1.
b00011 2
b01011111100101111000111111100001 3
b00001011111100101111000111111100 5
#8000000
0"
1#
b00010011110010111010011110111101 (
b00000000000000001001111001011101 )
b01101 *
0.
1/
b01101 2
b00010011110010111010011110111101 3
b00000000000000001001111001011101 5
#12000000
0#
1$
0&
b00000000000000000000000111110001 (
b10001100000000000000000000000111 )
b00110 *
0/
10
b00110 2
b00000000000000000000000111110001 3
04
b10001100000000000000000000000111 5
#16000000
0$
1%
0'
b11110001010011011110001011110100 (
b01111000101001101111000101111010 )
b00011 *
00
11
b00011 2
b11110001010011011110001011110100 3
b01111000101001101111000101111010 5
06
#20000000
1!
0%
b01100111101000101110010011111011 (
b00100111110110000000000000000000 )
b10011 *
1-
01
b10011 2
b01100111101000101110010011111011 3
b00100111110110000000000000000000 5
#24000000
0!
1"
b11010101000111011001111001011110 (
b00000000000000000000101010100011 )
0-
1.
b11010101000111011001111001011110 3
b00000000000000000000101010100011 5
#28000000
0"
1#
b11110000000111010001110100110000 (
b00000000000000000000000000000111 )
b11100 *
0.
1/
b11100 2
b11110000000111010001110100110000 3
b00000000000000000000000000000111 5
#32000000
0#
1$
1'
b00000000000000000000000111110001 (
b10001100000000000000000000000111 )
b00110 *
0/
10
b00110 2
b00000000000000000000000111110001 3
b10001100000000000000000000000111 5
16
#36000000
0$
1%
0'
b11101010000010101001001100101010 (
b01110101000001010100100110010101 )
b10111 *
00
11
b10111 2
b11101010000010101001001100101010 3
b01110101000001010100100110010101 5
06
#40000000
1!
0%
b01001000000110110010101101011001 (
b01100101011010110010000000000000 )
b01101 *
1-
01
b01101 2
b01001000000110110010101101011001 3
b01100101011010110010000000000000 5
#44000000
0!
1"
1'
b01001001001110010100000001110001 (
b00000000000000000000000000000000 )
b11111 *
0-
1.
b11111 2
b01001001001110010100000001110001 3
b00000000000000000000000000000000 5
16
#48000000
0"
1#
b00011011011011000001111100100001 (
b00000000000000000000011011011011 )
b10010 *
0.
1/
b10010 2
b00011011011011000001111100100001 3
b00000000000000000000011011011011 5
#52000000
0#
1$
b00000000000000000000000111110001 (
b10001100000000000000000000000111 )
b00110 *
0/
10
b00110 2
b00000000000000000000000111110001 3
b10001100000000000000000000000111 5
#56000000
0$
1%
0'
b11100001010001110110001101100000 (
b01110000101000111011000110110000 )
b01010 *
00
11
b01010 2
b11100001010001110110001101100000 3
b01110000101000111011000110110000 5
06
#60000000
1!
0%
b01001001001010001111011100101111 (
b01010001111011100101111000000000 )
b01001 *
1-
01
b01001 2
b01001001001010001111011100101111 3
b01010001111011100101111000000000 5
#64000000
0!
1"
1'
b01100111110100000010110110010011 (
b00000011001111101000000101101100 )
b00101 *
0-
1.
b00101 2
b01100111110100000010110110010011 3
b00000011001111101000000101101100 5
16
#68000000
0"
1#
0'
b01010101011101101101100010010000 (
b00101010101110110110110001001000 )
b00001 *
0.
1/
b00001 2
b01010101011101101101100010010000 3
b00101010101110110110110001001000 5
06
#72000000
0#
1$
1'
b00000000000000000000000111110001 (
b10001100000000000000000000000111 )
b00110 *
0/
10
b00110 2
b00000000000000000000000111110001 3
b10001100000000000000000000000111 5
16
#76000000
0$
1%
b10011101101110110001100011110101 (
b01001110110111011000110001111010 )
b01000 *
00
11
b01000 2
b10011101101110110001100011110101 3
b01001110110111011000110001111010 5
#80000000
1!
0%
b11110101010110100100100000101001 (
b10100100000000000000000000000000 )
b11010 *
1-
01
b11010 2
b11110101010110100100100000101001 3
b10100100000000000000000000000000 5
#84000000
0!
1"
0'
b00001111111110111101010110101010 (
b00000000000000000000001111111110 )
b10010 *
0-
1.
b10010 2
b00001111111110111101010110101010 3
b00000000000000000000001111111110 5
06
#88000000
0"
1#
1'
b11110000001001111001100111000111 (
b00000000000000000000000000111000 )
b11001 *
0.
1/
b11001 2
b11110000001001111001100111000111 3
b00000000000000000000000000111000 5
16
#92000000
0#
1$
b00000000000000000000000111110001 (
b10001100000000000000000000000111 )
b00110 *
0/
10
b00110 2
b00000000000000000000000111110001 3
b10001100000000000000000000000111 5
#96000000
0$
1%
0'
b01100111010100001010001011010000 (
b00110011101010000101000101101000 )
b10010 *
00
11
b10010 2
b01100111010100001010001011010000 3
b00110011101010000101000101101000 5
06
#100000000
1!
0%
b00100101111000000111100101000000 (
b00000000000000000000000000000000 )
b11011 *
1-
01
b11011 2
b00100101111000000111100101000000 3
b00000000000000000000000000000000 5
#104000000
0!
1"
b00000000111010011101100010000100 (
b00000000000000000000000000111010 )
b10010 *
0-
1.
b10010 2
b00000000111010011101100010000100 3
b00000000000000000000000000111010 5
#108000000
0"
1#
1'
b00111111010110000001110011001001 (
b00000000001111110101100000011100 )
b01000 *
0.
1/
b01000 2
b00111111010110000001110011001001 3
b00000000001111110101100000011100 5
16
#112000000
0#
1$
b00000000000000000000000111110001 (
b10001100000000000000000000000111 )
b00110 *
0/
10
b00110 2
b00000000000000000000000111110001 3
b10001100000000000000000000000111 5
#116000000
0$
1%
b11001111110101100011100010000011 (
b01100111111010110001110001000001 )
b10000 *
00
11
b10000 2
b11001111110101100011100010000011 3
b01100111111010110001110001000001 5
#120000000
1!
0%
b10001101101111011101001000011111 (
b10001101101111011101001000011111 )
b00000 *
1-
01
b00000 2
b10001101101111011101001000011111 3
b10001101101111011101001000011111 5
#124000000
0!
1"
0'
b10001100010110110011101001000110 (
b00000110001011011001110100100011 )
b00001 *
0-
1.
b00001 2
b10001100010110110011101001000110 3
b00000110001011011001110100100011 5
06
#128000000
0"
1#
b01000111101110010111100001100000 (
b00000000000000010001111011100101 )
b01110 *
0.
1/
b01110 2
b01000111101110010111100001100000 3
b00000000000